[
  {
    "num": "1",
    "ara": "وَالْعَادِيَاتِ ضَبْحًا",
    "eng": "By the racers, panting,",
    "ban": "ভাবো ঊর্ধ্বশ্বাসে ধাবমানদের কথা,"
  },
  {
    "num": "2",
    "ara": "فَالْمُورِيَاتِ قَدْحًا",
    "eng": "And the producers of sparks [when] striking",
    "ban": "ফলে যারা আগুনের ফুলকি ছোড়ে আঘাতের ছোটে,"
  },
  {
    "num": "3",
    "ara": "فَالْمُغِيرَاتِ صُبْحًا",
    "eng": "And the chargers at dawn,",
    "ban": "আর যারা ভোরে অভিযান চালায়,"
  },
  {
    "num": "4",
    "ara": "فَأَثَرْنَ بِهِ نَقْعًا",
    "eng": "Stirring up thereby [clouds of] dust,",
    "ban": "আর তার ফলে যারা ধূলো উড়ায় --"
  },
  {
    "num": "5",
    "ara": "فَوَسَطْنَ بِهِ جَمْعًا",
    "eng": "Arriving thereby in the center collectively,",
    "ban": "তখন এর ফলে সৈন্যদলকে ভেদ করে যায়।"
  },
  {
    "num": "6",
    "ara": "إِنَّ الْإِنسَانَ لِرَبِّهِ لَكَنُودٌ",
    "eng": "Indeed mankind, to his Lord, is ungrateful.",
    "ban": "মানুষ নিশ্চয়ই তার প্রভুর প্রতি বড় অকৃতজ্ঞ,"
  },
  {
    "num": "7",
    "ara": "وَإِنَّهُ عَلَى ذَلِكَ لَشَهِيدٌ",
    "eng": "And indeed, he is to that a witness.",
    "ban": "আর সে আলবৎ এ বিষয়ে অবশ্য প্রত্যক্ষদশ।"
  },
  {
    "num": "8",
    "ara": "وَإِنَّهُ لِحُبِّ الْخَيْرِ لَشَدِيدٌ",
    "eng": "And indeed he is, in love of wealth, intense.",
    "ban": "আর নিঃসন্দেহ সে ধনসম্পদের মোহে দুরন্ত।"
  },
  {
    "num": "9",
    "ara": "أَفَلَا يَعْلَمُ إِذَا بُعْثِرَ مَا فِي الْقُبُورِ",
    "eng": "But does he not know that when the contents of the graves are scattered",
    "ban": "তবে কি সে জানে না যখন কবরগুলোয় যা আছে তা তোলা হবে,"
  },
  {
    "num": "10",
    "ara": "وَحُصِّلَ مَا فِي الصُّدُورِ",
    "eng": "And that within the breasts is obtained,",
    "ban": "এবং অন্তরে যা আছে তা প্রকাশ করা হবে?"
  },
  {
    "num": "11",
    "ara": "إِنَّ رَبَّهُم بِهِمْ يَوْمَئِذٍ لَّخَبِيرٌ",
    "eng": "Indeed, their Lord with them, that Day, is [fully] Acquainted.",
    "ban": "নিঃসন্দেহ তাদের প্রভু সেইদিন তাদের সন্বন্ধে সবিশেষে অবহিত থাকবেন।"
  }
]
